mhhs_validate/__init__.py
mhhs_validate/cli.py
mhhs_validate/py.typed
mhhs_validate-0.0.2.dist-info/LICENSE
mhhs_validate-0.0.2.dist-info/METADATA
mhhs_validate-0.0.2.dist-info/WHEEL
mhhs_validate-0.0.2.dist-info/entry_points.txt
mhhs_validate-0.0.2.dist-info/top_level.txt
mhhs_validate-0.0.2.dist-info/RECORD
