Metadata-Version: 2.1
Name: mhhs-validate
Version: 0.0.2
Summary: MHHS validator
Author-email: Oliver Russell <ojhrussell@gmail.com>
Maintainer-email: Oliver Russell <ojhrussell@gmail.com>
License: MIT License
Project-URL: homepage, https://github.com/leontrolski/mhhs-validate
Project-URL: documentation, https://github.com/leontrolski/mhhs-validate
Project-URL: repository, https://github.com/leontrolski/mhhs-validate.git
Classifier: Programming Language :: Python
Requires-Python: >=3.7
License-File: LICENSE
Requires-Dist: openapi-schema-validator ==0.6.*
Requires-Dist: requests ==2.*
